pymakcu/__init__.py
pymakcu/connection.py
pymakcu/controller.py
pymakcu/enums.py
pymakcu/mouse.py
pymakcu-0.1.2.dist-info/METADATA
pymakcu-0.1.2.dist-info/WHEEL
pymakcu-0.1.2.dist-info/top_level.txt
pymakcu-0.1.2.dist-info/RECORD
