Metadata-Version: 2.4
Name: pymakcu
Version: 0.1.2
Summary: Python library for controlling Makcu USB device via COM port
Home-page: https://github.com/NeuralAIM/pymakcu
Author: NeuralUser
Author-email: admin@neuralaim.ru
Classifier: Programming Language :: Python :: 3
Classifier: License :: OSI Approved :: Apache Software License
Classifier: Operating System :: OS Independent
Classifier: Topic :: System :: Hardware
Classifier: Topic :: System :: Hardware :: Hardware Drivers
Requires-Python: >=3.7
Requires-Dist: pyserial>=3.5
Dynamic: author
Dynamic: author-email
Dynamic: classifier
Dynamic: description
Dynamic: description-content-type
Dynamic: home-page
Dynamic: requires-dist
Dynamic: requires-python
Dynamic: summary
